swt
tests
