Metadata-Version: 2.1
Name: swt-nlp
Version: 0.0.53
Summary: simple nlp pipeline
Home-page: UNKNOWN
Author: @muuusiiik
Author-email: muuusiiikd@gmail.com
License: Apache Software License 2.0
Platform: UNKNOWN
Classifier: License :: OSI Approved :: Apache Software License
Classifier: Programming Language :: Python :: 3
Classifier: Programming Language :: Python :: 3.7
Requires-Python: >=3.7
License-File: LICENSE
